{"name":"Union Populaire Républicaine","meetings":[{"date":"16/05/2025","location":"Kaysersberg"},{"date":"17/05/2025","location":"Montigny-la-Resle"},{"date":"18/05/2025","location":"Béziers"},{"date":"20/05/2025","location":"Les Ponts-de-Cé"},{"date":"21/05/2025","location":"Londres"},{"date":"23/05/2025","location":"Kaysersberg"},{"date":"24/05/2025","location":"Perpignan"},{"date":"24/05/2025","location":"Lyon"},{"date":"27/05/2025","location":"Amiens"},{"date":"27/05/2025","location":"Amiens"},{"date":"30/05/2025","location":"Kaysersberg"},{"date":"30/05/2025","location":"Paris 13ème arrondissement"}]}